jDWM/Ainslie.py
jDWM/AxialInductionModel.py
jDWM/BoundaryCondition.py
jDWM/EddyViscosityModel.py
jDWM/FilterFunctions.py
jDWM/MeanderCompensator.py
jDWM/Solvers.py
jDWM/Wake.py
jDWM/__init__.py
jDWM/fAinslie.py
jDWM/futilities.py
jDWM/putilities.py
jDWM/utilities.py
jdwm-0.8.dist-info/licenses/LICENSE
jdwm-0.8.dist-info/METADATA
jdwm-0.8.dist-info/WHEEL
jdwm-0.8.dist-info/top_level.txt
jdwm-0.8.dist-info/RECORD
