Metadata-Version: 2.4
Name: jDWM
Version: 0.8
Summary: A Python implementation of the Dynamic Wake meandering (DWM) model
Home-page: https://gitlab.windenergy.dtu.dk/HAWC2Public/jdwm
Author: Jaime Liew
Maintainer: Mads M Pedersen
Maintainer-email: mmpe@dtu.dk
License: MIT
License-File: LICENSE
Requires-Dist: numpy
Requires-Dist: scipy
Requires-Dist: matplotlib
Requires-Dist: numba
Requires-Dist: tqdm
Requires-Dist: pytest
Requires-Dist: pytest-cov
Dynamic: author
Dynamic: home-page
Dynamic: license
Dynamic: license-file
Dynamic: maintainer
Dynamic: maintainer-email
Dynamic: requires-dist
Dynamic: summary
